pyshtools_win_mac-4.12.2.dist-info/METADATA
pyshtools_win_mac-4.12.2.dist-info/WHEEL
pyshtools/_SHTOOLS.cpython-311-darwin.so
pyshtools/__init__.py
pyshtools/backends/__init__.py
pyshtools/backends/backends.py
pyshtools/backends/ducc0_wrapper.py
pyshtools/backends/shtools.py
pyshtools/constants/__init__.py
pyshtools/constants/Earth.py
pyshtools/constants/Mars.py
pyshtools/constants/Mercury.py
pyshtools/constants/Moon.py
pyshtools/constants/Venus.py
pyshtools/constants/Vesta.py
pyshtools/constants/Ceres.py
pyshtools/constants/Eros.py
pyshtools/constants/Io.py
pyshtools/constants/Europa.py
pyshtools/constants/Ganymede.py
pyshtools/constants/Callisto.py
pyshtools/constants/Titan.py
pyshtools/constants/Enceladus.py
pyshtools/datasets/__init__.py
pyshtools/datasets/Mercury.py
pyshtools/datasets/Eros.py
pyshtools/datasets/Ceres.py
pyshtools/datasets/Vesta.py
pyshtools/datasets/Io.py
pyshtools/datasets/Europa.py
pyshtools/datasets/Ganymede.py
pyshtools/datasets/Callisto.py
pyshtools/datasets/Titan.py
pyshtools/datasets/Enceladus.py
pyshtools/datasets/Earth/__init__.py
pyshtools/datasets/Earth/Earth2012/__init__.py
pyshtools/datasets/Earth/Earth2014/__init__.py
pyshtools/datasets/Mars/__init__.py
pyshtools/datasets/Mars/historical/__init__.py
pyshtools/datasets/Mars/historical/gravity.py
pyshtools/datasets/Mars/historical/magnetic.py
pyshtools/datasets/Mars/historical/shape.py
pyshtools/datasets/Moon/__init__.py
pyshtools/datasets/Moon/historical/__init__.py
pyshtools/datasets/Moon/historical/gravity.py
pyshtools/datasets/Moon/historical/shape.py
pyshtools/datasets/Venus/__init__.py
pyshtools/datasets/Venus/historical/__init__.py
pyshtools/datasets/Venus/historical/shape.py
pyshtools/expand/__init__.py
pyshtools/expand/spharm_functions.py
pyshtools/gravmag/__init__.py
pyshtools/gravmag/mag_spectrum.py
pyshtools/legendre/__init__.py
pyshtools/legendre/legendre_functions.py
pyshtools/legendre/plm_index.py
pyshtools/rotate/__init__.py
pyshtools/shclasses/__init__.py
pyshtools/shclasses/shcoeffs.py
pyshtools/shclasses/shgeoid.py
pyshtools_win_mac-4.12.2.dist-info/RECORD
